Workbook

Sheet Summary
A1: TESLA, INC.
A2: Investment Banking Analysis
A3: As of: February 01, 2026
A5: Company: | B5: Tesla, Inc.
A6: Ticker: | B6: TSLA
A7: Current Stock Price: | B7: 350
A8: Shares Outstanding (mm): | B8: 3539
A10: Valuation Summary
A11: Method | B11: Low | C11: Mid | D11: High
A12: DCF Valuation (per share) | B12: =DCF!B50 -> 40.061205 | C12: =DCF!C50 -> 119.68565 | D12: =DCF!D50 -> 222.19999
A13: Comparable Companies (per share) | B13: =Comps!B34 -> 28.839192 | C13: =Comps!C34 -> 42.236621 | D13: =Comps!D34 -> 67.691735
A14: Precedent Transactions (per share) | B14: =Precedents!B30 -> 169.78014 | C14: =Precedents!C30 -> 193.62756 | D14: =Precedents!D30 -> 249.62882
A16: Recommendation
A17: Rating: | B17: =Memo!B5 -> HOLD
A18: Target Price: | B18: =Memo!B6 -> 80.961134
A19: Upside/Downside: | B19: =B18/B7-1 -> -0.76868247

Sheet Historical Financials
A1: TESLA, INC. - HISTORICAL FINANCIALS
A2: Source: Q4 2025 Earnings Report
A4: Income Statement ($mm)
B5: 2021 | C5: 2022 | D5: 2022 | E5: 2022 | F5: 2022
A6: Total Automotive Revenues | B6: 47232 | C6: 71462 | D6: 82419 | E6: 77070 | F6: 69526
A7: Energy Storage Revenues | B7: 2789 | C7: 3909 | D7: 6035 | E7: 10086 | F7: 12771
A8: Services and Other | B8: 3802 | C8: 6091 | D8: 8319 | E8: 10534 | F8: 12530
A9: Total Revenues | B9: =SUM(B5:B8) -> 55844 | C9: =SUM(C5:C8) -> 83484 | D9: =SUM(D5:D8) -> 98795 | E9: =SUM(E5:E8) -> 99712 | F9: =SUM(F5:F8) -> 96849
A11: Total Gross Profit | B11: 13606 | C11: 20853 | D11: 17660 | E11: 17450 | F11: 17094
A12: Gross Margin % | B12: =B11/B9 -> 0.24364301 | C12: =C11/C9 -> 0.24978439 | D12: =D11/D9 -> 0.17875399 | E12: =E11/E9 -> 0.17500401 | F12: =F11/F9 -> 0.17650156
A14: Operating Expenses | B14: 7083 | C14: 7197 | D14: 8769 | E14: 10374 | F14: 12739
A15: Income from Operations | B15: =B11-B14 -> 6523 | C15: =C11-C14 -> 13656 | D15: =D11-D14 -> 8891 | E15: =E11-E14 -> 7076 | F15: =F11-F14 -> 4355
A16: Operating Margin % | B16: =B15/B9 -> 0.11680754 | C16: =C15/C9 -> 0.16357625 | D16: =D15/D9 -> 0.089994433 | E16: =E15/E9 -> 0.070964377 | F16: =F15/F9 -> 0.044966907
A18: Net Income | B18: 5519 | C18: 12556 | D18: 14997 | E18: 7091 | F18: 3794
A19: Net Margin % | B19: =B18/B9 -> 0.09882888 | C19: =C18/C9 -> 0.15040008 | D19: =D18/D9 -> 0.15179918 | E19: =E18/E9 -> 0.071114811 | F19: =F18/F9 -> 0.039174385
A21: Adjusted EBITDA | B21: 11722 | C21: 19390 | D21: 16631 | E21: 16056 | F21: 14596
A22: EBITDA Margin % | B22: =B21/B9 -> 0.20990617 | C22: =C21/C9 -> 0.23226007 | D22: =D21/D9 -> 0.16833848 | E22: =E21/E9 -> 0.16102375 | F22: =F21/F9 -> 0.15070884
A25: Balance Sheet ($mm)
A26: Cash and Investments | B26: 17707 | C26: 22185 | D26: 29094 | E26: 36563 | F26: 44059
A27: Total Assets | F27: 137806
A28: Total Debt | B28: 7878 | C28: 7244 | D28: 7136 | E28: 8213 | F28: 8376
A29: Shareholders Equity | F29: 82137
A32: Cash Flow ($mm)
A33: Operating Cash Flow | B33: 11497 | C33: 14724 | D33: 13256 | E33: 14923 | F33: 14747
A34: Capital Expenditures | B34: -6514 | C34: -7163 | D34: -8899 | E34: -11342 | F34: -8527
A35: Free Cash Flow | B35: =B33+B34 -> 4983 | C35: =C33+C34 -> 7561 | D35: =D33+D34 -> 4357 | E35: =E33+E34 -> 3581 | F35: =F33+F34 -> 6220

Sheet 3-Statement Model
A1: TESLA, INC. - 3-STATEMENT FINANCIAL MODEL
A2: Projections: 2026E - 2030E
A4: Key Assumptions
A5: Revenue Growth Rate | C5: 0.12 | D5: 0.15 | E5: 0.18 | F5: 0.16 | G5: 0.14
A6: Gross Margin % | C6: 0.19 | D6: 0.21 | E6: 0.23 | F6: 0.24 | G6: 0.25
A7: OpEx as % of Revenue | C7: 0.13 | D7: 0.12 | E7: 0.11 | F7: 0.1 | G7: 0.09
A9: Income Statement ($mm)
B10: Historical 2025A | C10: 2026E | D10: 2027E | E10: 2028E | F10: 2029E | G10: 2030E
A11: Automotive Revenues | B11: 69526 | C11: =B11*(1+C$5) -> 77869.12 | D11: =C11*(1+D$5) -> 89549.488 | E11: =D11*(1+E$5) -> 105668.4 | F11: =E11*(1+F$5) -> 122575.34 | G11: =F11*(1+G$5) -> 139735.89
A12: Energy Storage Revenues | B12: 12771 | C12: =B12*1.3 -> 16602.3 | D12: =C12*1.35 -> 22413.105 | E12: =D12*1.25 -> 28016.381 | F12: =E12*1.2 -> 33619.657 | G12: =F12*1.15 -> 38662.606
A13: Services and Other | B13: 12530 | C13: =B13*1.2 -> 15036 | D13: =C13*1.22 -> 18343.92 | E13: =D13*1.18 -> 21645.826 | F13: =E13*1.15 -> 24892.699 | G13: =F13*1.12 -> 27879.823
A14: Total Revenues | B14: =SUM(B11:B13) -> 94827 | C14: =SUM(C11:C13) -> 109507.42 | D14: =SUM(D11:D13) -> 130306.51 | E14: =SUM(E11:E13) -> 155330.6 | F14: =SUM(F11:F13) -> 181087.7 | G14: =SUM(G11:G13) -> 206278.32
A16: Cost of Revenues | B16: =B14*(1-0.18) -> 77758.14 | C16: =C14*(1-C$6) -> 88701.01 | D16: =D14*(1-D$6) -> 102942.15 | E16: =E14*(1-E$6) -> 119604.56 | F16: =F14*(1-F$6) -> 137626.65 | G16: =G14*(1-G$6) -> 154708.74
A17: Gross Profit | B17: =B14-B16 -> 17068.86 | C17: =C14-C16 -> 20806.41 | D17: =D14-D16 -> 27364.368 | E17: =E14-E16 -> 35726.039 | F17: =F14-F16 -> 43461.047 | G17: =G14-G16 -> 51569.579
A19: Operating Expenses | B19: -12739 | C19: =C14*C$7*-1 -> -14235.965 | D19: =D14*D$7*-1 -> -15636.782 | E19: =E14*E$7*-1 -> -17086.366 | F19: =F14*F$7*-1 -> -18108.77 | G19: =G14*G$7*-1 -> -18565.048
A20: EBITDA | B20: =B17-B19 -> 29807.86 | C20: =C17-C19 -> 35042.374 | D20: =D17-D19 -> 43001.149 | E20: =E17-E19 -> 52812.405 | F20: =F17-F19 -> 61569.817 | G20: =G17-G19 -> 70134.627
A23: Depreciation & Amortization | B23: -6148 | C23: =C14*0.065 -> 7117.9823 | D23: =D14*0.06 -> 7818.3908 | E23: =E14*0.055 -> 8543.1831 | F23: =F14*0.05 -> 9054.3848 | G23: =G14*0.05 -> 10313.916
A24: EBIT | B24: =B20-B23 -> 35955.86 | C24: =C20-C23 -> 27924.392 | D24: =D20-D23 -> 35182.759 | E24: =E20-E23 -> 44269.222 | F24: =F20-F23 -> 52515.432 | G24: =G20-G23 -> 59820.712
A26: Interest Expense | B26: -338 | C26: -350 | D26: -360 | E26: -370 | F26: -380 | G26: -390
A27: Taxes | B27: =-(B24+B26)*0.21 -> -7479.7506 | C27: =-(C24+C26)*0.21 -> -5790.6223 | D27: =-(D24+D26)*0.21 -> -7312.7793 | E27: =-(E24+E26)*0.21 -> -9218.8366 | F27: =-(F24+F26)*0.21 -> -10948.441 | G27: =-(G24+G26)*0.21 -> -12480.449
A28: Net Income | B28: =B24+B26+B27 -> 28138.109 | C28: =C24+C26+C27 -> 21783.77 | D28: =D24+D26+D27 -> 27509.979 | E28: =E24+E26+E27 -> 34680.385 | F28: =F24+F26+F27 -> 41186.991 | G28: =G24+G26+G27 -> 46950.262
A31: Cash Flow Statement ($mm)
A32: Net Income | B32: =B28 -> 28138.109 | C32: =C28 -> 21783.77 | D32: =D28 -> 27509.979 | E32: =E28 -> 34680.385 | F32: =F28 -> 41186.991 | G32: =G28 -> 46950.262
A33: D&A | B33: =-B23 -> 6148 | C33: =-C23 -> -7117.9823 | D33: =-D23 -> -7818.3908 | E33: =-E23 -> -8543.1831 | F33: =-F23 -> -9054.3848 | G33: =-G23 -> -10313.916
A34: Change in NWC | B34: -500 | C34: =C14*0.02*-1 -> -2190.1484 | D34: =D14*0.02*-1 -> -2606.1303 | E34: =E14*0.02*-1 -> -3106.6121 | F34: =F14*0.02*-1 -> -3621.7539 | G34: =G14*0.02*-1 -> -4125.5663
A35: Operating Cash Flow | B35: =SUM(B32:B34) -> 33786.109 | C35: =SUM(C32:C34) -> 12475.639 | D35: =SUM(D32:D34) -> 17085.458 | E35: =SUM(E32:E34) -> 23030.59 | F35: =SUM(F32:F34) -> 28510.852 | G35: =SUM(G32:G34) -> 32510.78
A37: Capex | B37: -8527 | C37: =C14*0.075*-1 -> -8213.0565 | D37: =D14*0.07*-1 -> -9121.4559 | E37: =E14*0.065*-1 -> -10096.489 | F37: =F14*0.06*-1 -> -10865.262 | G37: =G14*0.055*-1 -> -11345.307
A38: Free Cash Flow | B38: =B35+B37 -> 25259.109 | C38: =C35+C37 -> 4262.5826 | D38: =D35+D37 -> 7964.0023 | E38: =E35+E37 -> 12934.101 | F38: =F35+F37 -> 17645.591 | G38: =G35+G37 -> 21165.473

Sheet DCF
A1: TESLA, INC. - DCF VALUATION ANALYSIS
A3: WACC Assumptions
A4: Risk-Free Rate | B4: 0.045
A5: Market Risk Premium | B5: 0.07
A6: Beta | B6: 2
A7: Cost of Equity | B7: =B4+B6*B5 -> 0.185
A8: Cost of Debt (after-tax) | B8: 0.04
A9: Target D/E Ratio | B9: 0.1
A10: WACC | B10: =B7/(1+B9)+B8*B9/(1+B9) -> 0.17181818
A12: Terminal Value Assumptions
A13: Terminal Growth Rate | B13: 0.035
A14: Terminal EBITDA Multiple | B14: 18
A17: Free Cash Flow Projections ($mm)
B18: 2026E | C18: 2027E | D18: 2028E | E18: 2029E | F18: 2030E
A19: Free Cash Flow | B19: ='3-Statement Model'!C38 -> 4262.5826 | C19: ='3-Statement Model'!D38 -> 7964.0023 | D19: ='3-Statement Model'!E38 -> 12934.101 | E19: ='3-Statement Model'!F38 -> 17645.591 | F19: ='3-Statement Model'!G38 -> 21165.473
A21: Discount Period | B21: 0.5 | C21: 1.5 | D21: 2.5 | E21: 3.5 | F21: 4.5
A22: Discount Factor | B22: =1/(1+$B$10)^B21 -> 0.92378283 | C22: =1/(1+$B$10)^C21 -> 0.7883329 | D22: =1/(1+$B$10)^D21 -> 0.67274336 | E22: =1/(1+$B$10)^E21 -> 0.57410217 | F22: =1/(1+$B$10)^F21 -> 0.48992427
A23: PV of FCF | B23: =B19*B22 -> 3937.7006 | C23: =C19*C22 -> 6278.285 | D23: =D19*D22 -> 8701.3304 | E23: =E19*E22 -> 10130.372 | F23: =F19*F22 -> 10369.479
A25: Sum of PV of FCF | B25: =SUM(B23:F23) -> 39417.167
A28: Terminal Value Calculation
A30: Method 1: Perpetuity Growth
A31: 2030E FCF | B31: =F19 -> 21165.473
A32: Terminal Value | B32: =B31*(1+B13)/(B10-B13) -> 160112.23
A33: PV of Terminal Value | B33: =B32*F22 -> 78442.868
A36: Method 2: Exit Multiple
A37: 2030E EBITDA | B37: ='3-Statement Model'!G20 -> 70134.627
A38: Terminal Value | B38: =B37*B14 -> 1262423.3
A39: PV of Terminal Value | B39: =B38*F22 -> 618491.81
A42: Enterprise Value Calculation
B43: Bear | C43: Base | D43: Bull
A44: PV of FCF (2026E-2030E) | B44: =B25 -> 39417.167 | C44: =B25 -> 39417.167 | D44: =B25 -> 39417.167
A45: PV of Terminal Value | B45: =B33*0.85 -> 66676.438 | C45: =(B33+B39)/2 -> 348467.34 | D45: =B39*1.15 -> 711265.58
A46: Enterprise Value | B46: =B44+B45 -> 106093.6 | C46: =C44+C45 -> 387884.51 | D46: =D44+D45 -> 750682.75
A47: Less: Net Debt | B47: =8376-44059 -> -35683 | C47: =B47 -> -35683 | D47: =B47 -> -35683
A48: Equity Value | B48: =B46-B47 -> 141776.6 | C48: =C46-C47 -> 423567.51 | D48: =D46-D47 -> 786365.75
A49: Shares Outstanding (mm) | B49: =Summary!B8 -> 3539 | C49: =Summary!B8 -> 3539 | D49: =Summary!B8 -> 3539
A50: Price per Share | B50: =B48/B49 -> 40.061205 | C50: =C48/C49 -> 119.68565 | D50: =D48/D49 -> 222.19999

Sheet Comps
A1: COMPARABLE COMPANIES ANALYSIS
A2: As of January 31, 2026
A4: Trading Multiples
A5: Company | B5: Ticker | C5: Market Cap ($mm) | D5: EV ($mm) | E5: EV/Revenue 2025E | F5: EV/EBITDA 2025E | G5: P/E 2025E | H5: Revenue Growth 2025E
A6: General Motors | B6: GM | C6: 58000 | D6: 120000 | E6: 0.45 | F6: 5.2 | G6: 6.5 | H6: 0.03
A7: Ford Motor | B7: F | C7: 42000 | D7: 145000 | E7: 0.38 | F7: 4.8 | G7: 7.2 | H7: 0.02
A8: Toyota Motor | B8: TM | C8: 280000 | D8: 310000 | E8: 0.95 | F8: 8.5 | G8: 10.5 | H8: 0.05
A9: BYD Company | B9: BYDDY | C9: 95000 | D9: 98000 | E9: 1.2 | F9: 14.5 | G9: 22 | H9: 0.28
A10: NIO Inc. | B10: NIO | C10: 18000 | D10: 19500 | E10: 1.8 | F10: 32 | G10: -1 | H10: 0.35
A11: Rivian | B11: RIVN | C11: 12000 | D11: 13500 | E11: 2.5 | F11: -1 | G11: -1 | H11: 0.45
A12: Lucid Group | B12: LCID | C12: 8000 | D12: 9200 | E12: 8.5 | F12: -1 | G12: -1 | H12: 0.52
A14: Mean | E14: =AVERAGE(E6:E12) -> 2.2542857 | F14: =AVERAGEIF(F6:F12,">0") -> 13 | G14: =AVERAGEIF(G6:G12,">0") -> 11.55 | H14: =AVERAGE(H6:H12) -> 0.24285714
A15: Median | E15: =MEDIAN(E6:E12) -> 1.2 | F15: =MEDIAN(F6:F8,F9:F9) -> 6.85 | G15: =MEDIAN(G6:G8,G9:G9) -> 8.85 | H15: =MEDIAN(H6:H12) -> 0.28
A16: 25th Percentile | E16: =QUARTILE(E6:E12,1) -> 0.7 | F16: =QUARTILE(F6:F12,1) -> 1.9 | G16: =QUARTILE(G6:G12,1) -> -1
A17: 75th Percentile | E17: =QUARTILE(E6:E12,3) -> 2.15 | F17: =QUARTILE(F6:F12,3) -> 11.5 | G17: =QUARTILE(G6:G12,3) -> 8.85
A20: TESLA VALUATION
A21: 2025E Revenue ($mm) | B21: ='3-Statement Model'!B14 -> 94827
A22: 2025E EBITDA ($mm) | B22: ='3-Statement Model'!B20 -> 29807.86
A23: 2025E Net Income ($mm) | B23: ='3-Statement Model'!B28 -> 28138.109
A24: Net Debt ($mm) | B24: =8376-44059 -> -35683
A27: Implied Valuation
B28: Low | C28: Mid | D28: High
A29: EV/Revenue Multiple | B29: =E16 -> 0.7 | C29: =E15 -> 1.2 | D29: =E17 -> 2.15
A30: Implied Enterprise Value | B30: =B21*B29 -> 66378.9 | C30: =B21*C29 -> 113792.4 | D30: =B21*D29 -> 203878.05
A31: Less: Net Debt | B31: =B24 -> -35683 | C31: =B24 -> -35683 | D31: =B24 -> -35683
A32: Implied Equity Value | B32: =B30-B31 -> 102061.9 | C32: =C30-C31 -> 149475.4 | D32: =D30-D31 -> 239561.05
A33: Shares Outstanding (mm) | B33: =Summary!B8 -> 3539 | C33: =Summary!B8 -> 3539 | D33: =Summary!B8 -> 3539
A34: Implied Price per Share | B34: =B32/B33 -> 28.839192 | C34: =C32/C33 -> 42.236621 | D34: =D32/D33 -> 67.691735

Sheet Precedents
A1: PRECEDENT TRANSACTIONS ANALYSIS
A2: EV Automotive & Technology Sector M&A (2020-2025)
A4: Transaction Overview
A5: Date | B5: Target | C5: Acquirer | D5: Deal Value ($mm) | E5: EV/Revenue | F5: EV/EBITDA | G5: Premium % | H5: Synergies ($mm)
A6: Apr-2024 | B6: Waymo Fleet | C6: Alphabet | D6: 18000 | E6: 6.5 | F6: 28 | G6: 0.35 | H6: 500
A7: Sep-2023 | B7: Cruise (Stake) | C7: GM | D7: 12000 | E7: 8.2 | F7: 35 | G7: 0.28 | H7: 300
A8: Jun-2023 | B8: Argo AI | C8: Ford/VW | D8: 4000 | E8: 5.5 | F8: -1 | G8: 0.2 | H8: 150
A9: Mar-2022 | B9: Aurora Innovation | C9: Various | D9: 13000 | E9: 12.5 | F9: -1 | G9: 0.42 | H9: 400
A10: Nov-2021 | B10: Zoox | C10: Amazon | D10: 1300 | E10: 4.8 | F10: -1 | G10: 0.38 | H10: 200
A11: Aug-2020 | B11: Self-Driving Unit | C11: Uber/Aurora | D11: 4000 | E11: 7.2 | F11: -1 | G11: 0.3 | H11: 250
A13: Mean | E13: =AVERAGE(E6:E11) -> 7.45 | F13: =AVERAGE(F6:F11) -> 9.8333333 | G13: =AVERAGE(G6:G11) -> 0.32166667
A14: Median | E14: =MEDIAN(E6:E11) -> 6.85 | F14: =MEDIAN(F6:F11) -> -1 | G14: =MEDIAN(G6:G11) -> 0.325
A17: TESLA IMPLIED VALUATION
A18: 2025E Revenue ($mm) | B18: ='3-Statement Model'!B14 -> 94827
A19: Net Debt ($mm) | B19: =8376-44059 -> -35683
A22: Implied Valuation
B23: Low | C23: Mid | D23: High
A24: EV/Revenue Multiple | B24: =E13*0.8 -> 5.96 | C24: =E14 -> 6.85 | D24: =E13*1.2 -> 8.94
A25: Implied Enterprise Value | B25: =B18*B24 -> 565168.92 | C25: =B18*C24 -> 649564.95 | D25: =B18*D24 -> 847753.38
A26: Less: Net Debt | B26: =B19 -> -35683 | C26: =B19 -> -35683 | D26: =B19 -> -35683
A27: Control Premium (M&A Only) | B27: 0 | C27: 0 | D27: 0
A28: Implied Equity Value | B28: =B25-B26 -> 600851.92 | C28: =C25-C26 -> 685247.95 | D28: =D25-D26 -> 883436.38
A29: Shares Outstanding (mm) | B29: =Summary!B8 -> 3539 | C29: =Summary!B8 -> 3539 | D29: =Summary!B8 -> 3539
A30: Implied Price per Share | B30: =B28/B29 -> 169.78014 | C30: =C28/C29 -> 193.62756 | D30: =D28/D29 -> 249.62882

Sheet LBO Analysis
A1: LEVERAGED BUYOUT ANALYSIS
A3: Transaction Assumptions
A4: Purchase Price per Share | B4: 350
A5: Shares Outstanding (mm) | B5: =Summary!B8 -> 3539
A6: Equity Purchase Price | B6: =B4*B5 -> 1238650
A7: Plus: Transaction Fees (2%) | B7: =B6*0.02 -> 24773
A8: Total Uses | B8: =B6+B7 -> 1263423
A10: Sources of Funds
A11: Equity Contribution (%) | B11: 0.4
A12: Equity Amount | B12: =B8*B11 -> 505369.2
A13: Debt Financing | B13: =B8-B12 -> 758053.8
A16: Debt Structure
A17: Tranche | B17: Amount ($mm) | C17: % of Total | D17: Rate | E17: Maturity
A18: Senior Secured | B18: =B13*0.5 -> 379026.9 | C18: =B18/B13 -> 0.5 | D18: 0.065 | E18: 7
A19: Senior Unsecured | B19: =B13*0.3 -> 227416.14 | C19: =B19/B13 -> 0.3 | D19: 0.085 | E19: 8
A20: Subordinated Debt | B20: =B13*0.2 -> 151610.76 | C20: =B20/B13 -> 0.2 | D20: 0.11 | E20: 10
A21: Total Debt | B21: =SUM(B18:B20) -> 758053.8
A24: Exit Scenarios (Year 5)
B25: Bear | C25: Base | D25: Bull
A26: Exit EBITDA Multiple | B26: 15 | C26: 18 | D26: 22
A27: 2030E EBITDA | B27: ='3-Statement Model'!G20 -> 70134.627 | C27: ='3-Statement Model'!G20 -> 70134.627 | D27: ='3-Statement Model'!G20 -> 70134.627
A28: Enterprise Value at Exit | B28: =B26*B27 -> 1052019.4 | C28: =C26*C27 -> 1262423.3 | D28: =D26*D27 -> 1542961.8
A29: Less: Net Debt at Exit | B29: 20000 | C29: 15000 | D29: 10000
A30: Equity Value at Exit | B30: =B28-B29 -> 1032019.4 | C30: =C28-C29 -> 1247423.3 | D30: =D28-D29 -> 1532961.8
A32: Returns Analysis
A33: Initial Equity Investment | B33: =B12 -> 505369.2 | C33: =B12 -> 505369.2 | D33: =B12 -> 505369.2
A34: Exit Equity Value | B34: =B30 -> 1032019.4 | C34: =C30 -> 1247423.3 | D34: =D30 -> 1532961.8
A35: Cash-on-Cash (MOIC) | B35: =B34/B33 -> 2.0421098 | C35: =C34/C33 -> 2.4683406 | D35: =D34/D33 -> 3.0333503
A36: IRR | B36: =((B35)^(1/5))-1 -> 0.15349527 | C36: =((C35)^(1/5))-1 -> 0.19806675 | D36: =((D35)^(1/5))-1 -> 0.2484884
A39: Cash Flow Sweep Analysis
A40: Year | B40: 2026 | C40: 2027 | D40: 2028 | E40: 2029 | F40: 2030
A41: Free Cash Flow | B41: ='3-Statement Model'!C38 -> 4262.5826 | C41: ='3-Statement Model'!D38 -> 7964.0023 | D41: ='3-Statement Model'!E38 -> 12934.101 | E41: ='3-Statement Model'!F38 -> 17645.591 | F41: ='3-Statement Model'!G38 -> 21165.473
A42: Mandatory Amortization (5%) | B42: =-B13*0.05 -> -37902.69 | C42: =-B13*0.05 -> -37902.69 | D42: =-B13*0.05 -> -37902.69 | E42: =-B13*0.05 -> -37902.69 | F42: =-B13*0.05 -> -37902.69
A43: Cash Available for Sweep | B43: =B41+B42 -> -33640.107 | C43: =C41+C42 -> -29938.688 | D43: =D41+D42 -> -24968.589 | E43: =E41+E42 -> -20257.099 | F43: =F41+F42 -> -16737.217
A44: Optional Prepayment (50%) | B44: =B43*0.5 -> -16820.054 | C44: =C43*0.5 -> -14969.344 | D44: =D43*0.5 -> -12484.295 | E44: =E43*0.5 -> -10128.55 | F44: =F43*0.5 -> -8368.6086
A45: Total Debt Paydown | B45: =B42+B44 -> -54722.744 | C45: =C42+C44 -> -52872.034 | D45: =D42+D44 -> -50386.985 | E45: =E42+E44 -> -48031.24 | F45: =F42+F44 -> -46271.299
A46: Remaining Debt Balance | B46: =B13+B45 -> 703331.06 | C46: =B46+C45 -> 650459.02 | D46: =C46+D45 -> 600072.04 | E46: =D46+E45 -> 552040.8 | F46: =E46+F45 -> 505769.5

Sheet M&A Analysis
A1: M&A / STRATEGIC ANALYSIS
A3: Strategic Rationale
A4: 1. Market Leadership in EV Technology
A5: 2. Vertical Integration & Manufacturing Excellence
A6: 3. AI & Autonomous Driving Leadership
A7: 4. Energy Storage Growth Platform
A8: 5. Global Manufacturing & Distribution Network
A10: Revenue Synergies ($mm)
B11: Year 1 | C11: Year 2 | D11: Year 3 | E11: Year 4 | F11: Year 5
A12: Cross-selling to existing customers | B12: 500 | C12: 1200 | D12: 2000 | E12: 2800 | F12: 3500
A13: New market penetration | B13: 300 | C13: 800 | D13: 1500 | E13: 2200 | F13: 3000
A14: Technology licensing | B14: 200 | C14: 500 | D14: 900 | E14: 1400 | F14: 2000
A15: Total Revenue Synergies | B15: =SUM(B12:B14) -> 1000 | C15: =SUM(C12:C14) -> 2500 | D15: =SUM(D12:D14) -> 4400 | E15: =SUM(E12:E14) -> 6400 | F15: =SUM(F12:F14) -> 8500
A18: Cost Synergies ($mm)
A19: Procurement & supply chain | B19: 400 | C19: 900 | D19: 1300 | E19: 1600 | F19: 1800
A20: Duplicate overhead elimination | B20: 600 | C20: 1200 | D20: 1500 | E20: 1700 | F20: 1800
A21: Manufacturing efficiencies | B21: 300 | C21: 700 | D21: 1100 | E21: 1500 | F21: 1800
A22: R&D consolidation | B22: 200 | C22: 400 | D22: 600 | E22: 800 | F22: 1000
A23: Total Cost Synergies | B23: =SUM(B19:B22) -> 1500 | C23: =SUM(C19:C22) -> 3200 | D23: =SUM(D19:D22) -> 4500 | E23: =SUM(E19:E22) -> 5600 | F23: =SUM(F19:F22) -> 6400
A25: Total Synergies (EBITDA Impact) | B25: =B15*0.2+B23 -> 1700 | C25: =C15*0.2+C23 -> 3700 | D25: =D15*0.2+D23 -> 5380 | E25: =E15*0.2+E23 -> 6880 | F25: =F15*0.2+F23 -> 8100
A28: Accretion / Dilution Analysis
A29: Acquirer 2026E EPS | B29: 8.5
A30: Tesla 2026E EPS | B30: ='3-Statement Model'!C28/Summary!B8 -> 6.1553461
A31: Purchase Price per Share | B31: 350
A32: Tesla Shares Outstanding (mm) | B32: =Summary!B8 -> 3539
A33: Exchange Ratio (Acquirer shares) | B33: 2
A34: New Shares Issued (mm) | B34: =B32*B33 -> 7078
A35: Acquirer Shares Pre-Deal (mm) | B35: 1000
A36: Pro Forma Shares (mm) | B36: =B34+B35 -> 8078
A38: Pro Forma EPS Calculation
A39: Acquirer Stand-Alone EPS | B39: =B29 -> 8.5
A40: Tesla Contribution | B40: =(B30*B32)/B36 -> 2.6966786
A41: Synergies Contribution (Year 1) | B41: =(B25*(1-0.21))/B36 -> 0.16625402
A42: Pro Forma EPS | B42: =B39+B40+B41 -> 11.362933
A44: Accretion / (Dilution) | B44: =B42/B29-1 -> 0.3368156

Sheet Memo
A1: INVESTMENT MEMORANDUM
A2: TESLA, INC. (NASDAQ: TSLA)
A3: Date: February 01, 2026
A5: RECOMMENDATION: | B5: HOLD
A6: TARGET PRICE (DCF + Comps Avg): | B6: =(DCF!C50+Comps!C34)/2 -> 80.961134
A7: CURRENT PRICE: | B7: =Summary!B7 -> 350
A8: UPSIDE/(DOWNSIDE): | B8: =B6/B7-1 -> -0.76868247
A11: EXECUTIVE SUMMARY
A12: Tesla represents a transformational investment at the intersection of automotive,
A13: artificial intelligence, energy storage, and robotics. While the company faces near-term
A14: headwinds from automotive margin compression and delivery challenges, the long-term
A15: value proposition remains compelling driven by:
A17: • Leadership position in autonomous driving technology (FSD)
A18: • Rapidly scaling energy storage business (49% YoY growth)
A19: • Optimus humanoid robot platform entering production
A20: • Strong balance sheet with $44.1B cash and investments
A21: • Vertical integration advantages in manufacturing and AI infrastructure
A24: KEY INVESTMENT HIGHLIGHTS
A26: Strengths
... A49: KEY FINANCIAL METRICS
A51: Metric | B51: 2025A | C51: 2026E | D51: 2027E
A52: Revenue ($mm) | B52: ='Historical Financials'!F9 -> 96849 | C52: ='3-Statement Model'!C14 -> 109507.42 | D52: ='3-Statement Model'!D14 -> 130306.51
A53: EBITDA ($mm) | B53: ='Historical Financials'!F21 -> 14596 | C53: ='3-Statement Model'!C20 -> 35042.374 | D53: ='3-Statement Model'!D20 -> 43001.149
A54: Net Income ($mm) | B54: ='Historical Financials'!F18 -> 3794 | C54: ='3-Statement Model'!C28 -> 21783.77 | D54: ='3-Statement Model'!D28 -> 27509.979
A55: FCF ($mm) | B55: ='Historical Financials'!F35 -> 6220 | C55: ='3-Statement Model'!C38 -> 4262.5826 | D55: ='3-Statement Model'!D38 -> 7964.0023
A56: EBITDA Margin | B56: =B53/B52 -> 0.15070884 | C56: =C53/C52 -> 0.32 | D56: =D53/D52 -> 0.33
A59: CONCLUSION
A61: We maintain a HOLD rating on Tesla with a traditional valuation target of $81 based on
A62: DCF and comparable companies analysis. However, this ~77% downside from current levels
A63: reflects the market pricing in significant optionality for AI, robotics, and energy storage
A64: that traditional models struggle to capture. Risk/reward is balanced at current levels.
A66: Key Catalysts to Monitor:
A67: • Cybercab production ramp and Robotaxi expansion (H1 2026)
A68: • Optimus Gen 3 unveiling and production timeline (Q1 2026)
A69: • Energy storage deployment trajectory and margins
A70: • FSD regulatory approvals in China and Europe
A71: • Q1 2026 delivery numbers and automotive margin trends

Sheet Sensitivity
A1: SENSITIVITY ANALYSIS
A3: DCF Sensitivity - Terminal Growth vs WACC
B4: WACC → | C4: 0.12 | D4: 0.14 | E4: 0.16 | F4: 0.175 | G4: 0.19 | H4: 0.21
A5: Terminal Growth ↓ | B5: 0.025 | C5: =(SUM(DCF!B23:F23)+((DCF!F19*(1+0.025))/(0.12-0.025))*DCF!F22-8376+44059)/Summary!B8 -> 52.834525 | D5: =(SUM(DCF!B23:F23)+((DCF!F19*(1+0.025))/(0.14-0.025))*DCF!F22-8376+44059)/Summary!B8 -> 47.336474 | E5: =(SUM(DCF!B23:F23)+((DCF!F19*(1+0.025))/(0.16-0.025))*DCF!F22-8376+44059)/Summary!B8 -> 43.467475 | F5: =(SUM(DCF!B23:F23)+((DCF!F19*(1+0.025))/(0.175-0.025))*DCF!F22-8376+44059)/Summary!B8 -> 41.242801 | G5: =(SUM(DCF!B23:F23)+((DCF!F19*(1+0.025))/(0.19-0.025))*DCF!F22-8376+44059)/Summary!B8 -> 39.422613 | H5: =(SUM(DCF!B23:F23)+((DCF!F19*(1+0.025))/(0.21-0.025))*DCF!F22-8376+44059)/Summary!B8 -> 37.454842
B6: 0.03 | C6: =(SUM(DCF!B23:F23)+((DCF!F19*(1+0.03))/(0.12-0.03))*DCF!F22-8376+44059)/Summary!B8 -> 54.753628 | D6: =(SUM(DCF!B23:F23)+((DCF!F19*(1+0.03))/(0.14-0.03))*DCF!F22-8376+44059)/Summary!B8 -> 48.656738 | E6: =(SUM(DCF!B23:F23)+((DCF!F19*(1+0.03))/(0.16-0.03))*DCF!F22-8376+44059)/Summary!B8 -> 44.435814 | F6: =(SUM(DCF!B23:F23)+((DCF!F19*(1+0.03))/(0.175-0.03))*DCF!F22-8376+44059)/Summary!B8 -> 42.034253 | G6: =(SUM(DCF!B23:F23)+((DCF!F19*(1+0.03))/(0.19-0.03))*DCF!F22-8376+44059)/Summary!B8 -> 40.082986 | H6: =(SUM(DCF!B23:F23)+((DCF!F19*(1+0.03))/(0.21-0.03))*DCF!F22-8376+44059)/Summary!B8 -> 37.98718
B7: 0.035 | C7: =(SUM(DCF!B23:F23)+((DCF!F19*(1+0.035))/(0.12-0.035))*DCF!F22-8376+44059)/Summary!B8 -> 56.898508 | D7: =(SUM(DCF!B23:F23)+((DCF!F19*(1+0.035))/(0.14-0.035))*DCF!F22-8376+44059)/Summary!B8 -> 50.102741 | E7: =(SUM(DCF!B23:F23)+((DCF!F19*(1+0.035))/(0.16-0.035))*DCF!F22-8376+44059)/Summary!B8 -> 45.481619 | F7: =(SUM(DCF!B23:F23)+((DCF!F19*(1+0.035))/(0.175-0.035))*DCF!F22-8376+44059)/Summary!B8 -> 42.882238 | G7: =(SUM(DCF!B23:F23)+((DCF!F19*(1+0.035))/(0.19-0.035))*DCF!F22-8376+44059)/Summary!B8 -> 40.785964 | H7: =(SUM(DCF!B23:F23)+((DCF!F19*(1+0.035))/(0.21-0.035))*DCF!F22-8376+44059)/Summary!B8 -> 38.549937
B8: 0.04 | C8: =(SUM(DCF!B23:F23)+((DCF!F19*(1+0.04))/(0.12-0.04))*DCF!F22-8376+44059)/Summary!B8 -> 59.311498 | D8: =(SUM(DCF!B23:F23)+((DCF!F19*(1+0.04))/(0.14-0.04))*DCF!F22-8376+44059)/Summary!B8 -> 51.693344 | E8: =(SUM(DCF!B23:F23)+((DCF!F19*(1+0.04))/(0.16-0.04))*DCF!F22-8376+44059)/Summary!B8 -> 46.614576 | F8: =(SUM(DCF!B23:F23)+((DCF!F19*(1+0.04))/(0.175-0.04))*DCF!F22-8376+44059)/Summary!B8 -> 43.793037 | G8: =(SUM(DCF!B23:F23)+((DCF!F19*(1+0.04))/(0.19-0.04))*DCF!F22-8376+44059)/Summary!B8 -> 41.535807 | H8: =(SUM(DCF!B23:F23)+((DCF!F19*(1+0.04))/(0.21-0.04))*DCF!F22-8376+44059)/Summary!B8 -> 39.145798
B9: 0.045 | C9: =(SUM(DCF!B23:F23)+((DCF!F19*(1+0.045))/(0.12-0.045))*DCF!F22-8376+44059)/Summary!B8 -> 62.04622 | D9: =(SUM(DCF!B23:F23)+((DCF!F19*(1+0.045))/(0.14-0.045))*DCF!F22-8376+44059)/Summary!B8 -> 53.45138 | E9: =(SUM(DCF!B23:F23)+((DCF!F19*(1+0.045))/(0.16-0.045))*DCF!F22-8376+44059)/Summary!B8 -> 47.84605 | F9: =(SUM(DCF!B23:F23)+((DCF!F19*(1+0.045))/(0.175-0.045))*DCF!F22-8376+44059)/Summary!B8 -> 44.773897 | G9: =(SUM(DCF!B23:F23)+((DCF!F19*(1+0.045))/(0.19-0.045))*DCF!F22-8376+44059)/Summary!B8 -> 42.337363 | H9: =(SUM(DCF!B23:F23)+((DCF!F19*(1+0.045))/(0.21-0.045))*DCF!F22-8376+44059)/Summary!B8 -> 39.777771
A12: Comparable Companies - EV/Revenue Sensitivity
B13: EV/Revenue Multiple → | C13: 0.8 | D13: 1.2 | E13: 1.6 | F13: 2 | G13: 2.4 | H13: 2.8
A14: Revenue ($B) ↓ | B14: 90000 | C14: =((90000*0.8)-(-35683))/Summary!B8 -> 30.427522 | D14: =((90000*1.2)-(-35683))/Summary!B8 -> 40.599887 | E14: =((90000*1.6)-(-35683))/Summary!B8 -> 50.772252 | F14: =((90000*2)-(-35683))/Summary!B8 -> 60.944617 | G14: =((90000*2.4)-(-35683))/Summary!B8 -> 71.116982 | H14: =((90000*2.8)-(-35683))/Summary!B8 -> 81.289347
B15: 100000 | C15: =((100000*0.8)-(-35683))/Summary!B8 -> 32.688047 | D15: =((100000*1.2)-(-35683))/Summary!B8 -> 43.990675 | E15: =((100000*1.6)-(-35683))/Summary!B8 -> 55.293303 | F15: =((100000*2)-(-35683))/Summary!B8 -> 66.595931 | G15: =((100000*2.4)-(-35683))/Summary!B8 -> 77.898559 | H15: =((100000*2.8)-(-35683))/Summary!B8 -> 89.201187
B16: 110000 | C16: =((110000*0.8)-(-35683))/Summary!B8 -> 34.948573 | D16: =((110000*1.2)-(-35683))/Summary!B8 -> 47.381464 | E16: =((110000*1.6)-(-35683))/Summary!B8 -> 59.814354 | F16: =((110000*2)-(-35683))/Summary!B8 -> 72.247245 | G16: =((110000*2.4)-(-35683))/Summary!B8 -> 84.680136 | H16: =((110000*2.8)-(-35683))/Summary!B8 -> 97.113026
B17: 120000 | C17: =((120000*0.8)-(-35683))/Summary!B8 -> 37.209099 | D17: =((120000*1.2)-(-35683))/Summary!B8 -> 50.772252 | E17: =((120000*1.6)-(-35683))/Summary!B8 -> 64.335405 | F17: =((120000*2)-(-35683))/Summary!B8 -> 77.898559 | G17: =((120000*2.4)-(-35683))/Summary!B8 -> 91.461712 | H17: =((120000*2.8)-(-35683))/Summary!B8 -> 105.02487
B18: 130000 | C18: =((130000*0.8)-(-35683))/Summary!B8 -> 39.469624 | D18: =((130000*1.2)-(-35683))/Summary!B8 -> 54.16304 | E18: =((130000*1.6)-(-35683))/Summary!B8 -> 68.856457 | F18: =((130000*2)-(-35683))/Summary!B8 -> 83.549873 | G18: =((130000*2.4)-(-35683))/Summary!B8 -> 98.243289 | H18: =((130000*2.8)-(-35683))/Summary!B8 -> 112.93671
A21: LBO Returns - Exit Multiple vs Exit Year
B22: Exit Multiple → | C22: 14 | D22: 16 | E22: 18 | F22: 20 | G22: 22 | H22: 24
A23: Exit Year ↓ | B23: 3 | C23: =(((14*25000-15000)/535680)^(1/3))-1 -> -0.14484181 | D23: =(((16*25000-15000)/535680)^(1/3))-1 -> -0.10425354 | E23: =(((18*25000-15000)/535680)^(1/3))-1 -> -0.067043757 | F23: =(((20*25000-15000)/535680)^(1/3))-1 -> -0.032586592 | G23: =(((22*25000-15000)/535680)^(1/3))-1 -> -0.00042331736 | H23: =(((24*25000-15000)/535680)^(1/3))-1 -> 0.029793496
B24: 4 | C24: =(((14*25000-15000)/535680)^(1/4))-1 -> -0.11072754 | D24: =(((16*25000-15000)/535680)^(1/4))-1 -> -0.079256155 | E24: =(((18*25000-15000)/535680)^(1/4))-1 -> -0.050716448 | F24: =(((20*25000-15000)/535680)^(1/4))-1 -> -0.024540873 | G24: =(((22*25000-15000)/535680)^(1/4))-1 -> -0.00031750483 | H24: =(((24*25000-15000)/535680)^(1/4))-1 -> 0.022262921
B25: 5 | C25: =(((14*25000-15000)/535680)^(1/5))-1 -> -0.089609169 | D25: =(((16*25000-15000)/535680)^(1/5))-1 -> -0.06392411 | E25: =(((18*25000-15000)/535680)^(1/5))-1 -> -0.040783225 | F25: =(((20*25000-15000)/535680)^(1/5))-1 -> -0.019681358 | G25: =(((22*25000-15000)/535680)^(1/5))-1 -> -0.00025401193 | H25: =(((24*25000-15000)/535680)^(1/5))-1 -> 0.017771035
B26: 6 | C26: =(((14*25000-15000)/535680)^(1/6))-1 -> -0.075252365 | D26: =(((16*25000-15000)/535680)^(1/6))-1 -> -0.053561171 | E26: =(((18*25000-15000)/535680)^(1/6))-1 -> -0.0341034 | F26: =(((20*25000-15000)/535680)^(1/6))-1 -> -0.01642824 | G26: =(((22*25000-15000)/535680)^(1/6))-1 -> -0.00021168109 | H26: =(((24*25000-15000)/535680)^(1/6))-1 -> 0.014787414
B27: 7 | C27: =(((14*25000-15000)/535680)^(1/7))-1 -> -0.064859097 | D27: =(((16*25000-15000)/535680)^(1/7))-1 -> -0.046088906 | E27: =(((18*25000-15000)/535680)^(1/7))-1 -> -0.029303634 | F27: =(((20*25000-15000)/535680)^(1/7))-1 -> -0.014097976 | G27: =(((22*25000-15000)/535680)^(1/7))-1 -> -0.00018144367 | H27: =(((24*25000-15000)/535680)^(1/7))-1 -> 0.012661614
